fcs_client_lib.py
fcsapi_websocket-4.0.0.dist-info/licenses/LICENSE
fcsapi_websocket-4.0.0.dist-info/METADATA
fcsapi_websocket-4.0.0.dist-info/WHEEL
fcsapi_websocket-4.0.0.dist-info/top_level.txt
fcsapi_websocket-4.0.0.dist-info/RECORD
