Metadata-Version: 2.4
Name: fcsapi-websocket
Version: 4.0.0
Summary: Real-time WebSocket client for Python library for Forex, Cryptocurrency, and Stock market data from FCS API
Author-email: FCS API <support@fcsapi.com>
License: MIT
Project-URL: Homepage, https://fcsapi.com
Project-URL: Documentation, https://fcsapi.com/document/stock-api
Project-URL: Repository, https://github.com/fcsapi/websocket-python
Project-URL: Issues, https://github.com/fcsapi/websocket-python/issues
Keywords: fcs,fcsapi,forex,cryptocurrency,crypto,stock,realtime,websocket,market-data,trading,bitcoin,ethereum
Classifier: Development Status :: 5 - Production/Stable
Classifier: Intended Audience :: Developers
Classifier: License :: OSI Approved :: MIT License
Classifier: Operating System :: OS Independent
Classifier: Programming Language :: Python :: 3
Classifier: Programming Language :: Python :: 3.8
Classifier: Programming Language :: Python :: 3.9
Classifier: Programming Language :: Python :: 3.10
Classifier: Programming Language :: Python :: 3.11
Classifier: Programming Language :: Python :: 3.12
Classifier: Topic :: Office/Business :: Financial
Classifier: Topic :: Office/Business :: Financial :: Investment
Classifier: Topic :: Software Development :: Libraries :: Python Modules
Requires-Python: >=3.8
License-File: LICENSE
Requires-Dist: websocket-client>=1.0.0
Provides-Extra: dev
Requires-Dist: pytest>=7.0.0; extra == "dev"
Requires-Dist: pytest-cov>=4.0.1; extra == "dev"
Requires-Dist: black>=23.0.0; extra == "dev"
Requires-Dist: isort>=5.12.0; extra == "dev"
Requires-Dist: flake8>=6.0.0; extra == "dev"
Dynamic: license-file
